{
  "tasks": [
    {
      "header": "Что-то не важное",
      "description": "Кек",
      "date": "01.12.2020",
      "createDate": "2020-01-16T18:40:17.366Z",
      "id": 9
    },
    {
      "header": "Покушать",
      "description": "Или не покушать?",
      "date": "2020-01-16",
      "createDate": "2020-01-16T19:01:44.988Z",
      "id": 10
    },
    {
      "header": "Что-то очень важное",
      "description": "Ля-ля-ля-ля-ля-ля",
      "date": "2020-01-19",
      "createDate": "2020-01-16T21:38:16.742Z",
      "id": 12
    },
    {
      "header": "Матан",
      "description": "интегралы, пределы, ф. нескольких переменных",
      "date": "2020-01-18",
      "createDate": "2020-01-17T15:06:53.392Z",
      "id": 13
    },
    {
      "header": "жопа",
      "description": "lolo",
      "date": "3333-03-06",
      "createDate": "2020-01-17T15:58:58.964Z",
      "id": 16
    }
  ]
}